{"tid": 1, "uid": "40", "dmid": 8, "uclunum": 5, "uLabelList": [1, 4, 4, 3, 5, 3, 1, 4, 3, 3, 5, 4, 1, 4, 3, 3, 5, 4, 1, 4, 4, 4, 1, 5, 4, 3, 4, 4, 1, 1, 4, 4, 4, 1, 4, 4, 3, 3, 3, 3, 5, 5, 4, 4, 1, 4, 4, 4, 1, 1, 4, 3, 3, 4, 4, 3, 4, 3, 4, 5, 3, 4, 5, 1, 4, 3, 4, 4, 5, 5, 3, 4, 3, 4, 4, 5, 5, 1, 1, 4, 3, 3, 5, 4, 1, 4, 3, 3, 5, 4, 1, 4, 3, 3, 5, 4, 1, 4, 4, 4, 1, 5, 4, 3, 4, 4, 1, 1, 3, 3, 3, 1, 4, 3, 3, 3, 3, 3, 5, 5, 4, 4, 1, 4, 3, 3, 1, 1, 4, 3, 3, 5, 3, 4, 3, 4, 5, 3, 4, 5, 1, 4, 3, 4, 4, 5, 5, 3, 3, 3, 4, 4, 5, 5, 1, 1, 4, 3, 3, 5, 4, 1, 4, 3, 3, 5, 4, 1, 4, 3, 3, 5, 4, 1, 4, 4, 4, 1, 5, 4, 3, 4, 4, 1, 1, 3, 3, 3, 1, 4, 3, 3, 3, 3, 3, 5, 5, 4, 4, 1, 4, 3, 3, 1, 1, 4, 3, 3, 4, 5, 3, 4, 3, 4, 5, 3, 4, 5, 1, 4, 3, 4, 4, 5, 5, 3, 3, 3, 4, 4, 5, 5, 1, 3, 1, 4, 3, 3, 5, 4, 1, 4, 3, 3, 5, 4, 1, 4, 3, 3, 5, 4, 1, 4, 4, 3, 1, 5, 4, 3, 4, 4, 1, 1, 3, 3, 3, 1, 3, 3, 3, 3, 3, 3, 5, 5, 4, 4, 1, 4, 3, 3, 1, 1, 4, 3, 3, 4, 5, 3, 4, 3, 4, 5, 3, 4, 5, 1, 4, 3, 4, 4, 5, 5, 3, 3, 4, 4, 4, 5, 5, 1, 1, 3, 3, 3, 5, 4, 1, 3, 3, 3, 5, 4, 1, 3, 3, 3, 5, 4, 1, 4, 4, 4, 1, 5, 3, 3, 4, 3, 1, 1, 3, 3, 3, 1, 3, 3, 3, 3, 3, 3, 5, 5, 3, 4, 1, 4, 3, 3, 1, 1, 3, 3, 3, 3, 5, 3, 3, 3, 3, 5, 3, 4, 5, 1, 4, 3, 3, 4, 5, 5, 3, 3, 3, 4, 4, 5, 5, 1, 1, 4, 3, 3, 5, 4, 1, 4, 3, 3, 5, 4, 1, 4, 3, 3, 5, 4, 1, 4, 4, 4, 1, 5, 4, 3, 4, 4, 1, 1, 3, 3, 3, 1, 4, 3, 3, 3, 3, 3, 5, 5, 4, 4, 1, 4, 3, 3, 1, 1, 4, 3, 3, 4, 5, 3, 4, 3, 4, 5, 3, 4, 5, 1, 4, 3, 4, 4, 5, 5, 3, 3, 3, 4, 4, 5, 5, 1, 1, 4, 3, 3, 5, 4, 1, 4, 3, 3, 5, 4, 1, 4, 3, 3, 5, 4, 1, 4, 4, 4, 1, 5, 4, 3, 4, 4, 1, 1, 3, 3, 3, 1, 3, 3, 3, 3, 3, 3, 5, 5, 4, 4, 1, 4, 3, 3, 1, 1, 4, 3, 3, 4, 5, 3, 4, 3, 4, 5, 3, 4, 5, 1, 4, 3, 4, 4, 5, 5, 3, 4, 3, 4, 4, 5, 5, 1, 3, 3, 3, 5, 4, 1, 3, 3, 3, 5, 4, 1, 3, 3, 3, 5, 4, 1, 4, 4, 4, 1, 5, 3, 3, 4, 3, 3, 3, 1, 3, 3, 3, 3, 3, 3, 5, 5, 3, 4, 1, 4, 3, 3, 1, 1, 3, 3, 3, 3, 5, 3, 3, 3, 3, 5, 3, 3, 5, 1, 4, 3, 3, 4, 5, 5, 3, 3, 3, 4, 4, 5, 5, 1, 1, 4, 3, 3, 5, 4, 1, 4, 3, 3, 5, 4, 1, 4, 3, 3, 5, 4, 1, 4, 4, 4, 1, 5, 4, 3, 4, 4, 1, 1, 3, 1, 4, 3, 3, 3, 3, 3, 5, 5, 4, 4, 1, 4, 3, 3, 1, 1, 4, 3, 3, 4, 5, 3, 4, 4, 4, 5, 3, 4, 5, 1, 4, 3, 4, 4, 5, 5, 3, 3, 3, 4, 4, 5, 5, 1, 1, 4, 3, 3, 5, 4, 1, 4, 3, 3, 5, 4, 1, 4, 3, 3, 5, 4, 1, 4, 4, 4, 1, 5, 4, 3, 4, 4, 1, 1, 3, 3, 3, 1, 4, 3, 3, 3, 3, 3, 5, 5, 4, 4, 1, 4, 3, 3, 1, 1, 4, 3, 3, 4, 5, 3, 4, 3, 4, 5, 3, 4, 5, 1, 4, 3, 4, 4, 5, 5, 3, 3, 3, 4, 4, 5, 5, 1, 1, 4, 3, 3, 5, 4, 1, 4, 3, 3, 5, 4, 1, 4, 3, 3, 5, 4, 1, 4, 4, 4, 1, 5, 4, 3, 4, 4, 1, 1, 3, 3, 3, 1, 4, 3, 3, 3, 3, 3, 5, 5, 4, 4, 1, 4, 3, 3, 1, 1, 4, 3, 3, 4, 5, 3, 4, 3, 4, 5, 3, 4, 5, 1, 4, 3, 4, 4, 5, 5, 3, 3, 3, 4, 4, 5, 5, 1, 1, 4, 3, 3, 5, 4, 1, 4, 3, 3, 5, 4, 1, 4, 3, 3, 5, 4, 1, 4, 4, 4, 1, 5, 4, 3, 4, 4, 1, 1, 3, 3, 3, 1, 4, 3, 3, 3, 3, 3, 5, 5, 4, 4, 1, 4, 3, 3, 1, 1, 4, 3, 3, 4, 5, 3, 4, 3, 4, 5, 3, 4, 5, 1, 4, 3, 4, 4, 5, 5, 3, 3, 3, 4, 4, 5, 5, 1, 1, 4, 3, 3, 5, 4, 1, 4, 3, 3, 5, 4, 1, 4, 3, 3, 5, 4, 2, 4, 4, 4, 1, 5, 4, 3, 4, 4, 1, 1, 3, 3, 3, 1, 4, 3, 3, 3, 3, 3, 5, 5, 4, 4, 1, 4, 3, 1, 4, 3, 3, 4, 5, 3, 4, 3, 4, 5, 3, 4, 5, 1, 4, 3, 4, 4, 5, 5, 3, 3, 4, 4, 5, 5, 1, 1, 4, 3, 3, 5, 4, 1, 4, 3, 3, 5, 4, 1, 4, 3, 3, 5, 4, 1, 4, 4, 4, 1, 5, 4, 3, 4, 4, 1, 1, 3, 3, 3, 1, 4, 3, 3, 3, 3, 3, 5, 5, 4, 4, 1, 4, 3, 3, 1, 1, 4, 3, 3, 4, 5, 3, 4, 3, 4, 5, 3, 4, 5, 1, 4, 3, 4, 4, 5, 5, 3, 3, 3, 4, 4, 5, 5, 1], "time": 13.952, "dataName": "mnist64", "methodName": "lle"}